{
  "project_info": {
    "project_number": "109866582485",
    "project_id": "fly-checklist",
    "storage_bucket": "fly-checklist.firebasestorage.app"
  },
  "client": [
    {
      "client_info": {
        "mobilesdk_app_id": "1:109866582485:android:e01cd91000c4cc44f67d5c",
        "android_client_info": {
          "package_name": "br.dev.vitormelo.fly_checklist"
        }
      },
      "oauth_client": [
        {
          "client_id": "109866582485-7sct9p0229dvsfodh3tkgu6l2q81chtm.apps.googleusercontent.com",
          "client_type": 1,
          "android_info": {
            "package_name": "br.dev.vitormelo.fly_checklist",
            "certificate_hash": "7022bb9c09ae3640fa27a13ebbf28a383358118f"
          }
        },
        {
          "client_id": "109866582485-5cjn3i45k0to8ulghv4a7kt10et03sn3.apps.googleusercontent.com",
          "client_type": 3
        }
      ],
      "api_key": [
        {
          "current_key": "AIzaSyCJfDzMfvfoVhjYHIYQDyw_4_-Gix_4vFY"
        }
      ],
      "services": {
        "appinvite_service": {
          "other_platform_oauth_client": [
            {
              "client_id": "109866582485-5cjn3i45k0to8ulghv4a7kt10et03sn3.apps.googleusercontent.com",
              "client_type": 3
            }
          ]
        }
      }
    }
  ],
  "configuration_version": "1"
}